skip_trace/__about__.py
skip_trace/__init__.py
skip_trace/__main__.py
skip_trace/cli.py
skip_trace/config.py
skip_trace/exceptions.py
skip_trace/m.py
skip_trace/main.py
skip_trace/py.typed.py
skip_trace/schemas.py
skip_trace/analysis/__init__.py
skip_trace/analysis/content_scanner.py
skip_trace/analysis/evidence.py
skip_trace/analysis/ner.py
skip_trace/analysis/scoring.py
skip_trace/analysis/source_scanner.py
skip_trace/collectors/__init__.py
skip_trace/collectors/github.py
skip_trace/collectors/github_files.py
skip_trace/collectors/package_files.py
skip_trace/collectors/pypi.py
skip_trace/collectors/pypi_attestations.py
skip_trace/collectors/sigstore.py
skip_trace/collectors/urls.py
skip_trace/collectors/whois.py
skip_trace/reporting/__init__.py
skip_trace/reporting/json_reporter.py
skip_trace/reporting/md_reporter.py
skip_trace/utils/__init__.py
skip_trace/utils/cache.py
skip_trace/utils/cli_suggestions.py
skip_trace/utils/http_client.py
skip_trace/utils/safe_targz.py
skip_trace/utils/validation.py
skip_trace-0.1.1.dist-info/METADATA
skip_trace-0.1.1.dist-info/WHEEL
skip_trace-0.1.1.dist-info/entry_points.txt
skip_trace-0.1.1.dist-info/licenses/LICENSE
skip_trace-0.1.1.dist-info/RECORD
