Metadata-Version: 2.4
Name: skip-trace
Version: 0.1.1
Summary: Ownership Attribution for Python Packages
Project-URL: Homepage, https://github.com/matthewdeanmartin/skip-trace
Project-URL: Issues, https://github.com/matthewdeanmartin/skip-trace/issues
Author-email: Matthew Dean Martin <matthewdeanmartin@gmail.com>
License-Expression: MIT
License-File: LICENSE
Keywords: PEP 541,PyPI maintainers,package owners,package provenance,software supply chain
Classifier: Development Status :: 3 - Alpha
Classifier: License :: OSI Approved :: MIT License
Classifier: Operating System :: OS Independent
Classifier: Programming Language :: Python :: 3
Classifier: Programming Language :: Python :: 3.9
Classifier: Programming Language :: Python :: 3.10
Classifier: Programming Language :: Python :: 3.11
Classifier: Programming Language :: Python :: 3.12
Classifier: Programming Language :: Python :: 3.13
Classifier: Topic :: Security
Classifier: Topic :: Software Development :: Quality Assurance
Requires-Python: >=3.13
Requires-Dist: beautifulsoup4>=4.12.0
Requires-Dist: email-validator>=2.0.0
Requires-Dist: en-core-web-sm
Requires-Dist: httpx[http2]>=0.25.0
Requires-Dist: openai>=1.3.0
Requires-Dist: pip>=20
Requires-Dist: pygithub>=1.59.0
Requires-Dist: python-dotenv
Requires-Dist: python-dotenv>=1.0.0
Requires-Dist: python-whois>=0.8.0
Requires-Dist: pyyaml>=6.0
Requires-Dist: rich-argparse
Requires-Dist: rich>=13.0.0
Requires-Dist: sigstore>=1.0.0
Requires-Dist: spacy>=3.0.0
Requires-Dist: tldextract
Requires-Dist: tldextract>=5.0.0
Requires-Dist: tomli; python_version < '3.11'
Requires-Dist: whoisit>=1.2
